keyneg_mcp/__init__.py
keyneg_mcp/licensing.py
keyneg_mcp/server.py
keyneg_mcp-0.2.0.dist-info/METADATA
keyneg_mcp-0.2.0.dist-info/WHEEL
keyneg_mcp-0.2.0.dist-info/entry_points.txt
keyneg_mcp-0.2.0.dist-info/RECORD
