Metadata-Version: 2.4
Name: keyneg-mcp
Version: 0.2.0
Summary: MCP Server for KeyNeg sentiment analysis - the first general-purpose sentiment analysis tool for Claude, ChatGPT, and Gemini
Project-URL: Homepage, https://grandnasser.com
Project-URL: Repository, https://github.com/Osseni94/keyneg-mcp
Project-URL: Documentation, https://grandnasser.com/docs/keyneg-mcp
Author-email: Kaossara Osseni <admin@grandnasser.com>
License: MIT
Keywords: ai-tools,anthropic,claude,keyneg,mcp,model-context-protocol,nlp,sentiment-analysis
Classifier: Development Status :: 4 - Beta
Classifier: Intended Audience :: Developers
Classifier: License :: OSI Approved :: MIT License
Classifier: Programming Language :: Python :: 3
Classifier: Programming Language :: Python :: 3.10
Classifier: Programming Language :: Python :: 3.11
Classifier: Programming Language :: Python :: 3.12
Classifier: Topic :: Scientific/Engineering :: Artificial Intelligence
Classifier: Topic :: Text Processing :: Linguistic
Requires-Python: >=3.10
Requires-Dist: keyneg-enterprise-rs>=1.0.0
Requires-Dist: mcp>=1.0.0
Provides-Extra: dev
Requires-Dist: pytest-asyncio>=0.21; extra == 'dev'
Requires-Dist: pytest>=7.0; extra == 'dev'
